Workbook

Sheet Setup
B2: $0 to $1,000 Emergency Fund — 90 Day Blueprint
B3: Fill in the 5 yellow cells below. Everything else calculates automatically.
B5: YOUR 5 INPUTS — Fill in the yellow cells
B6: Input 1 | C6: Monthly take-home income | D6: 4000 | E6: After-tax dollars deposited each month
B7: Input 2 | C7: Monthly essential expenses | D7: 2800 | E7: Rent + utilities + food + transportation only
B8: Input 3 | C8: Amount already saved toward $1,000 | D8: 0 | E8: Enter 0 if starting from scratch
B9: Input 4 | C9: Pay frequency | D9: Bi-weekly | E9: Weekly / Bi-weekly / Semi-monthly / Monthly
B10: Input 5 | C10: Biggest obstacle to saving | D10: Spend before save | E10: Spend before save / Nothing left over / Unexpected expenses / Don't know where it goes
B12: YOUR SAVINGS MATH — Auto-calculated
C13: Monthly take-home | D13: =IF(D6="",0,D6) -> 4000
C14: Monthly essentials | D14: =IF(D7="",0,D7) -> 2800
C15: Monthly surplus (gap) | D15: =D13-D14 -> 1200
C16: Weekly savings capacity | D16: =ROUND(D15/4.33,0) -> 277
C17: Already saved | D17: =IF(D8="",0,D8) -> 0
C18: Remaining to $1,000 | D18: =MAX(0,1000-D17) -> 1000
C19: Weeks needed at capacity | D19: =IF(D16=0,"-",CEILING(D18/D16,1)) -> 4
C20: On track to hit $1,000? | D20: =IF(D19="-","Enter income",IF(D19<=13,"YES — on track","Stretch — see Money Sources")) -> YES — on track
B22: HOW TO USE THIS WORKBOOK
B23: You fill in 5 cells above — the workbook does the rest. Follow the 4 steps below, then use the tabs at the bottom each week until you hit $1,000.
B25: STEP 1 | C25: Fill in your 5 inputs above (yellow cells)
B26: → | C26: Input 1 — Your monthly take-home after taxes.
B27: → | C27: Input 2 — Essential expenses only: rent, utilities, food, transportation.
B28: → | C28: Input 3 — Enter 0 if starting from scratch, or any amount already saved.
B29: → | C29: Input 4 — How often you receive a paycheck.
B30: → | C30: Input 5 — Pick the obstacle that best describes why saving is hard for you.
B32: STEP 2 | C32: Check your savings math (auto-calculated above)
B33: → | C33: Your 'weekly savings capacity' is the key number — this is what you can realistically save per week.
B34: → | C34: If it reads $0 or negative, go to the Money Sources tab for ways to increase income or cut expenses.
B35: → | C35: The 'On track?' row tells you immediately whether a 90-day finish is realistic at your current capacity.
B36: → | C36: You do not need to edit any cells in the savings math section — they update automatically.
B38: STEP 3 | C38: Open the 90-Day Calendar tab — follow week 1 only
... B48: → | C48: Review your gap number monthly — income and expenses change, so update Inputs 1 and 2.
B51: COLOR LEGEND
B52: Yellow cell | C52: Fill this in — it's your input
B53: Teal cell | C53: Auto-calculated — do not edit
B54: Purple cell | C54: Label / category tag
B55: Gray cell | C55: Pre-filled example or reference
B56: Amber cell | C56: Tip or important note
B57: Green cell | C57: On-track / completed status
B59: Total time to set up: ~10 min | Weekly check-in: ~2 min | Target: $1,000 in 90 days (13 weeks)

Sheet 90-Day Calendar
B2: 90-Day Savings Calendar — Week by Week
B3: Each week: make your deposit, check the box, watch your balance grow. Focus on one week at a time.
B5: Week | C5: Dates (fill in) | D5: Target Deposit | E5: Actual Deposit | F5: Running Total | G5: Done? | H5: Notes
B6: Week 1 | D6: =IFERROR(CEILING((1000-Setup!D17)/13,1),0) -> 77 | E6: 0 | F6: =Setup!D17+E6 -> 0
B7: Week 2 | D7: =IFERROR(CEILING((1000-Setup!D17)/13,1),0) -> 77 | E7: 0 | F7: =F6+E7 -> 0
B8: Week 3 | D8: =IFERROR(CEILING((1000-Setup!D17)/13,1),0) -> 77 | E8: 0 | F8: =F7+E8 -> 0
B9: Week 4 | D9: =IFERROR(CEILING((1000-Setup!D17)/13,1),0) -> 77 | E9: 0 | F9: =F8+E9 -> 0
B10: Week 5 | D10: =IFERROR(CEILING((1000-Setup!D17)/13,1),0) -> 77 | E10: 0 | F10: =F9+E10 -> 0
B11: Week 6 | D11: =IFERROR(CEILING((1000-Setup!D17)/13,1),0) -> 77 | E11: 0 | F11: =F10+E11 -> 0
B12: Week 7 | D12: =IFERROR(CEILING((1000-Setup!D17)/13,1),0) -> 77 | E12: 0 | F12: =F11+E12 -> 0
B13: Week 8 | D13: =IFERROR(CEILING((1000-Setup!D17)/13,1),0) -> 77 | E13: 0 | F13: =F12+E13 -> 0
B14: Week 9 | D14: =IFERROR(CEILING((1000-Setup!D17)/13,1),0) -> 77 | E14: 0 | F14: =F13+E14 -> 0
B15: Week 10 | D15: =IFERROR(CEILING((1000-Setup!D17)/13,1),0) -> 77 | E15: 0 | F15: =F14+E15 -> 0
B16: Week 11 | D16: =IFERROR(CEILING((1000-Setup!D17)/13,1),0) -> 77 | E16: 0 | F16: =F15+E16 -> 0
B17: Week 12 | D17: =IFERROR(CEILING((1000-Setup!D17)/13,1),0) -> 77 | E17: 0 | F17: =F16+E17 -> 0
B18: Week 13 | D18: =IFERROR(CEILING((1000-Setup!D17)/13,1),0) -> 77 | E18: 0 | F18: =F17+E18 -> 0
B19: TOTAL | D19: =SUM(D6:D18) -> 1001 | E19: =SUM(E6:E18) -> 0 | F19: =F18 -> 0
B21: Progress to $1,000 | D21: =TEXT(MIN(F18/1000,1),"0%")&" of $1,000 saved" -> 0% of $1,000 saved | F21: =IF(F18>=1000,"GOAL REACHED!",IF(F18>=750,"Almost there!",IF(F18>=500,"Halfway!","Keep going!"))) -> Keep going!
B23: Tip: Enter "X" or "Done" in the Done? column each week. Deposit into a separate savings account — not checking.

Sheet Gap Finder
B2: Gap Finder — Where Does Your Money Go?
B4: INCOME
B5: Primary job / salary | C5: =Setup!D6 -> 4000
B6: Side income (if any) | C6: 0
B7: Other income | C7: 0
B8: TOTAL INCOME | C8: =SUM(C5:C7) -> 4000
B10: ESSENTIAL EXPENSES (must-pay)
B11: Rent / Mortgage | C11: =Setup!D7*0.35 -> 980 | D11: Estimated from your Input 2
B12: Utilities (electric/gas/water) | C12: 0
B13: Groceries / Food | C13: 0
B14: Transportation | C14: 0 | D14: Gas, transit, car payment
B15: Phone | C15: 0
B16: Insurance | C16: 0 | D16: Health, car, renters
B17: Minimum debt payments | C17: 0 | D17: Credit cards, loans
B18: Other essentials | C18: 0
B19: TOTAL EXPENSES | C19: =SUM(C11:C18) -> 980
B21: YOUR GAP
B22: Monthly surplus (your gap) | C22: =C8-C19 -> 3020
B23: Weekly savings capacity | C23: =ROUND(C22/4.33,0) -> 697
B24: Daily savings capacity | C24: =ROUND(C22/30,0) -> 101
B26: Your weekly savings capacity = the target amount to deposit each week in the 90-Day Calendar.

Sheet Money Sources
B2: 12 Money Sources — Ranked Fastest to Slowest
B3: Check the boxes in column B for your top 3. Fastest cash sources are listed first. One action per source — do it this week.
B5: Use? | C5: Money Source | D5: Est. $ Range | E5: Time to Cash | F5: Your Action This Week
C6: Sell unused items | D6: $20–$300 | E6: Same day | F6: List 5 items on Facebook Marketplace today. Price 30% below retail for fast sale.
C7: Gig app (Uber/DoorDash) | D7: $50–$200/wk | E7: 2–3 days | F7: Sign up today, complete orientation, do first delivery this weekend.
C8: Return unused purchases | D8: $20–$150 | E8: 2–5 days | F8: Check last 90 days of purchases. Return anything unworn or unopened.
C9: Cancel unused subscriptions | D9: $10–$100/mo | E9: Immediate | F9: Log into bank, find recurring charges, cancel any you forgot about.
C10: Odd jobs (TaskRabbit/Craigslist) | D10: $50–$300 | E10: 3–7 days | F10: Post 1 service offer today: moving help, cleaning, yard work, assembly.
C11: Cash in gift cards | D11: $10–$200 | E11: 1–2 days | F11: Check drawers/wallet for unused gift cards. Sell on Raise.com for 80–90% cash.
C12: Ask for overtime | D12: $50–$300 | E12: Next paycheck | F12: Email your manager today asking about available overtime or extra shifts.
C13: Negotiate a bill | D13: $10–$50/mo | E13: 1–2 days | F13: Call internet or phone provider. Ask for loyalty discount or current promotions.
C14: Plasma/blood donation | D14: $50–$100 | E14: Same day | F14: Find nearest center at donatingplasma.org. First donation often pays more.
C15: Tax refund (if owed) | D15: $200–$1,500 | E15: 1–3 weeks | F15: File taxes immediately if not done. Use IRS Free File if income under $73k.
C16: Side hustle launch | D16: $100–$500+ | E16: 2–4 weeks | F16: Pick one skill (writing, design, tutoring, bookkeeping). Post one offer on Fiverr.
C17: Ask for a raise | D17: $100–$500/mo | E17: Next cycle | F17: Document 3 wins from last 6 months. Request a meeting with your manager this week.
B19: Strategy: Check your top 3, execute one action per source this week. Green = fastest cash. Amber = medium. Red = longer term.

Sheet Obstacle Strategy
B2: Obstacle Strategy — Your Personalized Fix
B3: =IF(Setup!D10="","Fill in Input 5 on Setup tab","Your obstacle: "&Setup!D10) -> Your obstacle: Spend before save
B5: If your obstacle is: "Spend before save"
B6: → | C6: Tactic 1 — Automate immediately | D6: Set up a recurring transfer for the morning AFTER your payday, before you touch the money. Log into your bank today and schedule it.
B7: → | C7: Tactic 2 — Open a separate account | D7: Move savings to a different bank (Ally, Marcus). Out of sight = out of reach. No debit card for the savings account.
B8: → | C8: Tactic 3 — Pay yourself first | D8: Treat savings like rent — non-negotiable. Transfer happens before any discretionary spending, every single payday.
B9: → | C9: Tactic 4 — Remove friction barriers | D9: Delete your savings account from your primary bank's app. Make it slightly inconvenient to access the money.
B10: → | C10: Tactic 5 — Weekly amount, not monthly | D10: Commit to $X per week, not per month. Smaller, more frequent wins build the habit faster.
B12: If your obstacle is: "Nothing left over"
B13: → | C13: Tactic 1 — Find your 3 biggest leaks | D13: Print last month's bank statement. Highlight the top 3 categories besides essentials. Those are your first cuts.
B14: → | C14: Tactic 2 — The $1/day challenge | D14: Start with just $1 per day ($30/month). It builds the habit without feeling like sacrifice. Scale up after 30 days.
B15: → | C15: Tactic 3 — Cut one subscription today | D15: Go to your bank app, find recurring charges. Cancel the one you use least. Average person saves $40–$80/mo.
B16: → | C16: Tactic 4 — Activate a money source | D16: If expenses truly equal income, you need more income — not more cuts. Go to the Money Sources tab and activate your top-3 today.
B17: → | C17: Tactic 5 — No-spend 3 days per week | D17: Pick Mon/Wed/Fri as no-spend days. No coffee, no eating out, no impulse buys. Bank the difference each week.
B19: If your obstacle is: "Unexpected expenses"
B20: → | C20: Tactic 1 — Build a $200 buffer first | D20: Before targeting $1,000, get to $200. This covers 80% of common unexpected costs and stops credit card dependency.
B21: → | C21: Tactic 2 — Predict the unpredictable | D21: List recurring 'surprises': car registration, annual subscriptions, medical copays. Divide by 12 and save that monthly.
B22: → | C22: Tactic 3 — The replacement fund rule | D22: When you withdraw from the fund, activate your top money source immediately to replace it within 2 weeks.
B23: → | C23: Tactic 4 — Separate accounts by purpose | D23: One account = $200 buffer (accessible). One account = $800 growth fund (harder to access). Two buckets, two purposes.
B24: → | C24: Tactic 5 — Increase your credit card limit | D24: Call your card issuer and request a limit increase (do not increase spending). This is your backstop while the fund builds.
B26: If your obstacle is: "Don't know where it goes"
B27: → | C27: Tactic 1 — The 10-minute bank audit | D27: Right now: open your bank app, go to last month's transactions. Add up every non-essential charge. That total is your answer.
B28: → | C28: Tactic 2 — Cash envelope method | D28: Withdraw your weekly discretionary budget in cash. When the envelope is empty, spending stops. No math required.
B29: → | C29: Tactic 3 — One-category tracking | D29: Track only food spending for 2 weeks. Most people are shocked. One category is manageable; full budgeting feels overwhelming.
B30: → | C30: Tactic 4 — The 24-hour rule | D30: For any non-essential purchase over $20: wait 24 hours. Most impulse buys disappear. The money stays in your account.
B31: → | C31: Tactic 5 — Weekly 5-minute money check | D31: Every Sunday, spend 5 minutes reviewing the week's spending. Not to judge — just to see. Awareness alone reduces spending 10–15%.

Sheet Auto-Refill Setup
B2: Auto-Refill Setup — Keep Your Fund Full Forever
B3: Once you hit $1,000 — set up these 5 steps so the fund rebuilds itself automatically after any withdrawal.
B5: Step | C5: Action | D5: How to do it | E5: Done?
B6: 1 | C6: Open a dedicated high-yield savings account | D6: Open Ally Bank or Marcus by Goldman Sachs (no fees, 4%+ APY). Do NOT use your primary bank's savings account. Separate bank = less temptation.
B7: 2 | C7: Set up a recurring auto-transfer | D7: Log into your PRIMARY bank. Go to Transfers → Recurring. Set up a weekly transfer of your 'weekly savings capacity' (from Setup tab D16) to your new HYSA. Set the date to 1 day after payday.
B8: 3 | C8: Label the account 'Emergency Fund — Do Not Touch' | D8: In your HYSA app, rename the account. Psychological labeling reduces the chance of dipping into it for non-emergencies by over 50% (per behavioral finance research).
B9: 4 | C9: Set a low-balance alert at $800 | D9: In your HYSA, set an email/text alert when the balance drops below $800. This is your trigger to activate a money source from the Money Sources tab to refill.
B10: 5 | C10: Create a refill rule: withdraw = activate | D10: Write this rule somewhere visible: 'Every time I withdraw from the emergency fund, I activate my #1 money source the same day until the fund is back to $1,000.' This is the system that keeps the system working.
B12: Recommended HYSA: Ally Bank (ally.com) or Marcus by Goldman Sachs (marcus.com). Both offer 4%+ APY, no minimums, no fees. Setup takes 10 minutes.
B14: Next step after $1,000: See product 09 — Automate Your Finances in One Saturday ($37) — to automate your bills, savings, and investments the same way.
