Workbook

Sheet Setup
B2: Kill One Debt in 30 Days — Snowball Starter Kit
B3: Fill in your debts and 4 inputs below. The system selects your quick-win target automatically.
B5: YOUR INPUTS — Fill in the yellow cells
B6: Input 2 | C6: Extra monthly payment for debt | D6: 100 | E6: Amount available beyond all minimums each month
B7: Input 3 | C7: Which debt feels most crushing? | D7: Credit Card A | E7: Type the name from your debt table below
B8: Input 4 | C8: Ever negotiated with a creditor? | D8: No | E8: Yes / No / Not sure what that means
B9: Input 5 | C9: Biggest debt fear | D9: I'll never pay it all off | E9: I'll never pay it all off / I'll miss a payment / I don't know if I'm doing this right
B11: QUICK-WIN TARGET — Auto-selected from your debt table
C12: Quick-win debt (lowest balance) | D12: =IFERROR(INDEX('Debt Inventory'!B6:B15,MATCH(MIN('Debt Inventory'!C6:C15),'Debt Inventory'!C6:C15,0)),"Enter debts below") -> Enter debts below
C13: Balance to eliminate | D13: =IFERROR(MIN(IF('Debt Inventory'!C6:C15>0,'Debt Inventory'!C6:C15)),"—") -> 0
C14: Minimum payment | D14: =IFERROR(INDEX('Debt Inventory'!D6:D15,MATCH(MIN('Debt Inventory'!C6:C15),'Debt Inventory'!C6:C15,0)),"—") -> —
C15: Total monthly attack (min + extra) | D15: =IFERROR(D14+D6,"—") -> —
C16: Estimated months to kill it | D16: =IFERROR(CEILING(D13/D15,1),"—") -> —
C17: Your psychological choice (Input 3) | D17: =D7 -> Credit Card A
C18: Math choice = psychological choice? | D18: =IFERROR(IF(D12=D7,"YES — same debt","REVIEW: Math vs. feeling differ — see note"),"—") -> REVIEW: Math vs. feeling differ — see note
B20: HOW TO USE THIS WORKBOOK
B21: You fill in your debts and 4 yellow cells above — the workbook does the rest. Follow the 4 steps below. Your only job this week: kill debt #1.
B23: STEP 1 | C23: Enter all your debts in the Debt Inventory tab
B24: → | C24: Go to the Debt Inventory tab — enter every debt you owe (up to 10).
B25: → | C25: For each debt: creditor name, current balance, minimum monthly payment, and interest rate (APR).
B26: → | C26: Don't worry about being exact — estimates are fine to start.
B27: → | C27: Come back here after entering debts — your quick-win target will auto-populate above.
B28: → | C28: Input 2 above (extra monthly payment) is the most important number — even $25/month matters.
B30: STEP 2 | C30: Confirm your quick-win target (this tab, above)
B31: → | C31: The quick-win target auto-selects your lowest-balance debt — this is where you attack first.
B32: → | C32: Check if your psychological choice (Input 3) matches the math recommendation.
B33: → | C33: If they differ, review both options — but generally trust the math for fastest momentum.
B34: → | C34: All other debts get minimum payments only until debt #1 is eliminated.
B35: → | C35: Once debt #1 is gone, its payment amount rolls into debt #2 — that's the snowball.
... B49: → | C49: When debt #1 hits $0, go to the Snowball Schedule tab to confirm debt #2 becomes the new target.
B52: COLOR LEGEND
B53: Yellow cell | C53: Fill this in — your input
B54: Teal cell | C54: Auto-calculated — do not edit
B55: Coral cell | C55: Quick-win / action items
B56: Purple cell | C56: Label / category tag
B57: Gray cell | C57: Pre-filled example or reference
B58: Amber cell | C58: Tip or important note
B60: Setup time: ~10 min | Week 1 action: ~15 min (call + payment) | Goal: debt #1 at $0 in 30 days

Sheet Debt Inventory
B2: Debt Inventory — Enter All Your Debts Here
B3: List every debt. Smallest balance first is ideal but not required — the system sorts automatically.
B5: # | C5: Creditor / Debt Name | D5: Current Balance | E5: Min. Payment | F5: APR % | G5: Debt Type | H5: Snowball Order | I5: Status
B6: 1 | C6: Credit Card A | D6: 1200 | E6: 35 | F6: 24.99 | G6: Credit Card | H6: =IFERROR(IF(D6="","",RANK(D6,D6:D15,1)),"—") -> 2
B7: 2 | C7: Medical Bill | D7: 340 | E7: 25 | F7: 0 | G7: Medical | H7: =IFERROR(IF(D7="","",RANK(D7,D6:D15,1)),"—") -> 1
B8: 3 | C8: Personal Loan | D8: 3800 | E8: 95 | F8: 12.5 | G8: Personal Loan | H8: =IFERROR(IF(D8="","",RANK(D8,D6:D15,1)),"—") -> 3
B9: 4 | C9: Credit Card B | D9: 5500 | E9: 110 | F9: 21.99 | G9: Credit Card | H9: =IFERROR(IF(D9="","",RANK(D9,D6:D15,1)),"—") -> 4
B10: 5 | C10: Auto Loan | D10: 12000 | E10: 280 | F10: 6.9 | G10: Auto Loan | H10: =IFERROR(IF(D10="","",RANK(D10,D6:D15,1)),"—") -> 5
B11: 6 | H11: =IFERROR(IF(D11="","",RANK(D11,D6:D15,1)),"—")
B12: 7 | H12: =IFERROR(IF(D12="","",RANK(D12,D6:D15,1)),"—")
B13: 8 | H13: =IFERROR(IF(D13="","",RANK(D13,D6:D15,1)),"—")
B14: 9 | H14: =IFERROR(IF(D14="","",RANK(D14,D6:D15,1)),"—")
B15: 10 | H15: =IFERROR(IF(D15="","",RANK(D15,D6:D15,1)),"—")
C16: TOTALS | D16: =SUM(D6:D15) -> 22840 | E16: =SUM(E6:E15) -> 545
B18: DEBT SUMMARY
C19: Total debt balance | D19: =D16 -> 22840
C20: Total minimum payments/mo | D20: =E16 -> 545
C21: Extra payment (from Setup) | D21: =Setup!D6 -> 100
C22: Total monthly attack | D22: =D20+D21 -> 645
C23: Number of debts | D23: =COUNTA(C6:C15) -> 5
C24: Avg interest rate | D24: =IFERROR(AVERAGEIF(D6:D15,">0",F6:F15),0) -> 13.276
C26: Note: Enter APR as a number (e.g. 24.99 for 24.99%). Replace sample data with your actual debts. All rows are editable.

Sheet 30-Day Kill Plan
B2: 30-Day Kill Plan — Debt #1 Only
B3: One debt. Four weeks. Follow only this tab until debt #1 hits $0. Everything else gets minimums.
B5: TARGET DEBT
C6: Debt to kill | D6: =Setup!D12 -> Enter debts below
C7: Starting balance | D7: =Setup!D13 -> 0
C8: Monthly attack | D8: =Setup!D15 -> —
C9: Est. months to $0 | D9: =Setup!D16 -> —
B11: Week | C11: Action | D11: Details | E11: Done?
B12: Week 1 | C12: Call creditor + make first extra payment | D12: Call the number on the back of your card/statement. Use the Negotiation Scripts tab. Ask for a rate reduction. Then make your payment: minimum + all of your extra amount from Input 2.
B13: Week 2 | C13: Make your scheduled payment — no extra actions | D13: Pay exactly: minimum payment + extra payment amount. Set up autopay if you haven't already (see Auto-Pay checklist in Fear Reset tab). Do not touch this debt's balance mentally — just pay.
B14: Week 3 | C14: Make your scheduled payment + check balance | D14: Make the same payment as Week 2. Log in and check the actual balance. Update cell D7 above with the new balance. Confirm the estimated payoff month in Setup tab still looks right.
B15: Week 4 | C15: Final payment push — apply any windfalls | D15: Make your regular payment. If any extra money came in this month (overtime, sold item, refund), apply 100% of it to this debt. Update balance in D7. If at $0 — go to Snowball Schedule tab.
B17: MONTHLY BALANCE TRACKER
B18: Month | C18: Starting Balance | D18: Payments Made | E18: Ending Balance | F18: Done?
B19: Month 1 | E19: =IFERROR(C19-D19,"") -> 0
B20: Month 2 | E20: =IFERROR(C20-D20,"") -> 0
B21: Month 3 | E21: =IFERROR(C21-D21,"") -> 0
B22: Month 4 | E22: =IFERROR(C22-D22,"") -> 0
B23: Month 5 | E23: =IFERROR(C23-D23,"") -> 0
B24: Month 6 | E24: =IFERROR(C24-D24,"") -> 0
C26: When debt #1 reaches $0 in the Ending Balance column — celebrate, then open the Snowball Schedule tab to activate debt #2.

Sheet Snowball Schedule
B2: Full Snowball Payoff Schedule
B3: Reference only — shows all debts in sequence. No action needed here until debt #1 is gone.
B5: Order | C5: Creditor | D5: Balance | E5: Min. Payment | F5: Extra Payment | G5: Monthly Attack | H5: Est. Months | I5: Cumulative Mo.
B6: 1 | C6: =IFERROR(INDEX('Debt Inventory'!C6:C15,MATCH(1,'Debt Inventory'!H6:H15,0)),"—") -> Medical Bill | D6: =IFERROR(INDEX('Debt Inventory'!D6:D15,MATCH(1,'Debt Inventory'!H6:H15,0)),"") -> 340 | E6: =IFERROR(INDEX('Debt Inventory'!E6:E15,MATCH(1,'Debt Inventory'!H6:H15,0)),"") -> 25 | F6: =IFERROR(Setup!D6,0) -> 100 | G6: =IFERROR(E6+F6,"") -> 125 | H6: =IFERROR(IF(G6=0,"",CEILING(D6/G6,1)),"") -> 3 | I6: =IFERROR(H6,"") -> 3
B7: 2 | C7: =IFERROR(INDEX('Debt Inventory'!C6:C15,MATCH(2,'Debt Inventory'!H6:H15,0)),"—") -> Credit Card A | D7: =IFERROR(INDEX('Debt Inventory'!D6:D15,MATCH(2,'Debt Inventory'!H6:H15,0)),"") -> 1200 | E7: =IFERROR(INDEX('Debt Inventory'!E6:E15,MATCH(2,'Debt Inventory'!H6:H15,0)),"") -> 35 | F7: =IFERROR(F6+E6,"") -> 125 | G7: =IFERROR(E7+F7,"") -> 160 | H7: =IFERROR(IF(G7=0,"",CEILING(D7/G7,1)),"") -> 8 | I7: =IFERROR(I6+H7,"") -> 11
B8: 3 | C8: =IFERROR(INDEX('Debt Inventory'!C6:C15,MATCH(3,'Debt Inventory'!H6:H15,0)),"—") -> Personal Loan | D8: =IFERROR(INDEX('Debt Inventory'!D6:D15,MATCH(3,'Debt Inventory'!H6:H15,0)),"") -> 3800 | E8: =IFERROR(INDEX('Debt Inventory'!E6:E15,MATCH(3,'Debt Inventory'!H6:H15,0)),"") -> 95 | F8: =IFERROR(F7+E7,"") -> 160 | G8: =IFERROR(E8+F8,"") -> 255 | H8: =IFERROR(IF(G8=0,"",CEILING(D8/G8,1)),"") -> 15 | I8: =IFERROR(I7+H8,"") -> 26
B9: 4 | C9: =IFERROR(INDEX('Debt Inventory'!C6:C15,MATCH(4,'Debt Inventory'!H6:H15,0)),"—") -> Credit Card B | D9: =IFERROR(INDEX('Debt Inventory'!D6:D15,MATCH(4,'Debt Inventory'!H6:H15,0)),"") -> 5500 | E9: =IFERROR(INDEX('Debt Inventory'!E6:E15,MATCH(4,'Debt Inventory'!H6:H15,0)),"") -> 110 | F9: =IFERROR(F8+E8,"") -> 255 | G9: =IFERROR(E9+F9,"") -> 365 | H9: =IFERROR(IF(G9=0,"",CEILING(D9/G9,1)),"") -> 16 | I9: =IFERROR(I8+H9,"") -> 42
B10: 5 | C10: =IFERROR(INDEX('Debt Inventory'!C6:C15,MATCH(5,'Debt Inventory'!H6:H15,0)),"—") -> Auto Loan | D10: =IFERROR(INDEX('Debt Inventory'!D6:D15,MATCH(5,'Debt Inventory'!H6:H15,0)),"") -> 12000 | E10: =IFERROR(INDEX('Debt Inventory'!E6:E15,MATCH(5,'Debt Inventory'!H6:H15,0)),"") -> 280 | F10: =IFERROR(F9+E9,"") -> 365 | G10: =IFERROR(E10+F10,"") -> 645 | H10: =IFERROR(IF(G10=0,"",CEILING(D10/G10,1)),"") -> 19 | I10: =IFERROR(I9+H10,"") -> 61
B11: 6 | C11: =IFERROR(INDEX('Debt Inventory'!C6:C15,MATCH(6,'Debt Inventory'!H6:H15,0)),"—") -> — | D11: =IFERROR(INDEX('Debt Inventory'!D6:D15,MATCH(6,'Debt Inventory'!H6:H15,0)),"") | E11: =IFERROR(INDEX('Debt Inventory'!E6:E15,MATCH(6,'Debt Inventory'!H6:H15,0)),"") | F11: =IFERROR(F10+E10,"") -> 645 | G11: =IFERROR(E11+F11,"") | H11: =IFERROR(IF(G11=0,"",CEILING(D11/G11,1)),"") | I11: =IFERROR(I10+H11,"")
B12: 7 | C12: =IFERROR(INDEX('Debt Inventory'!C6:C15,MATCH(7,'Debt Inventory'!H6:H15,0)),"—") -> — | D12: =IFERROR(INDEX('Debt Inventory'!D6:D15,MATCH(7,'Debt Inventory'!H6:H15,0)),"") | E12: =IFERROR(INDEX('Debt Inventory'!E6:E15,MATCH(7,'Debt Inventory'!H6:H15,0)),"") | F12: =IFERROR(F11+E11,"") | G12: =IFERROR(E12+F12,"") | H12: =IFERROR(IF(G12=0,"",CEILING(D12/G12,1)),"") | I12: =IFERROR(I11+H12,"")
B13: 8 | C13: =IFERROR(INDEX('Debt Inventory'!C6:C15,MATCH(8,'Debt Inventory'!H6:H15,0)),"—") -> — | D13: =IFERROR(INDEX('Debt Inventory'!D6:D15,MATCH(8,'Debt Inventory'!H6:H15,0)),"") | E13: =IFERROR(INDEX('Debt Inventory'!E6:E15,MATCH(8,'Debt Inventory'!H6:H15,0)),"") | F13: =IFERROR(F12+E12,"") | G13: =IFERROR(E13+F13,"") | H13: =IFERROR(IF(G13=0,"",CEILING(D13/G13,1)),"") | I13: =IFERROR(I12+H13,"")
B14: 9 | C14: =IFERROR(INDEX('Debt Inventory'!C6:C15,MATCH(9,'Debt Inventory'!H6:H15,0)),"—") -> — | D14: =IFERROR(INDEX('Debt Inventory'!D6:D15,MATCH(9,'Debt Inventory'!H6:H15,0)),"") | E14: =IFERROR(INDEX('Debt Inventory'!E6:E15,MATCH(9,'Debt Inventory'!H6:H15,0)),"") | F14: =IFERROR(F13+E13,"") | G14: =IFERROR(E14+F14,"") | H14: =IFERROR(IF(G14=0,"",CEILING(D14/G14,1)),"") | I14: =IFERROR(I13+H14,"")
B15: 10 | C15: =IFERROR(INDEX('Debt Inventory'!C6:C15,MATCH(10,'Debt Inventory'!H6:H15,0)),"—") -> — | D15: =IFERROR(INDEX('Debt Inventory'!D6:D15,MATCH(10,'Debt Inventory'!H6:H15,0)),"") | E15: =IFERROR(INDEX('Debt Inventory'!E6:E15,MATCH(10,'Debt Inventory'!H6:H15,0)),"") | F15: =IFERROR(F14+E14,"") | G15: =IFERROR(E15+F15,"") | H15: =IFERROR(IF(G15=0,"",CEILING(D15/G15,1)),"") | I15: =IFERROR(I14+H15,"")
C16: TOTAL DEBT | D16: =SUM(D6:D15) -> 22840 | E16: =SUM(E6:E15) -> 545
C18: Snowball logic: when each debt hits $0, its full monthly attack amount rolls into the next debt. The "extra payment" grows with every win.
C20: Next step: Once all debts are eliminated, see product 09 — Automate Your Finances in One Saturday ($37) — to automate savings and investments the same way.

Sheet Negotiation Scripts
B2: Rate Negotiation Scripts — Word for Word
B3: Use whichever script matches your creditor type. Estimated call time: 8 minutes. Best time to call: Tuesday–Thursday, 10am–2pm.
B5: Script: Credit Card
B6: Before you call | C6: Have ready: account number, current balance, how long you've been a customer, your on-time payment history. Pull up a competitor's lower rate offer if you have one.
B7: Opening line | C7: "Hi, I've been a customer for [X years] and I always pay on time. I'm looking at my finances and working to pay down debt faster. I'd like to request a lower interest rate on my account."
B8: If they ask why | C8: "I've received offers from other cards at lower rates, and I'd prefer to stay with you. Reducing my rate would help me pay this balance off faster and keep me as a long-term customer."
B9: The ask | C9: "Can you reduce my APR from [current rate]% to something in the [target — 3–5% lower]% range?"
B10: If they say no | C10: "I understand. Is there a promotional rate or balance transfer option available? Or can you note my request and have a supervisor review it?"
B11: Close | C11: "Thank you. Can you email me confirmation of any changes made today? And can I ask — what would I need to do to qualify for a rate reduction in the future?"
B13: Script: Medical Debt
B14: Before you call | C14: Medical debt is the most negotiable. Hospitals write off large amounts. You can often settle for 30–50 cents on the dollar. Have your bill number and total amount ready.
B15: Opening line | C15: "Hi, I received a bill for [amount] from [provider name]. I want to pay this but I'm having financial difficulty. I'd like to discuss a reduction or payment plan."
B16: The ask — reduction | C16: "I can pay [30–50% of bill] as a lump sum today if you can accept that as payment in full. Can you authorize that?"
B17: The ask — plan | C17: "If a lump sum isn't possible, can you set up a payment plan with no interest? I can pay $[amount] per month."
B18: If they transfer you | C18: Ask to speak with the financial counselor or patient advocate — they have more authority than billing reps.
B19: Close | C19: "Can you send me written confirmation of the agreed amount before I make payment? I won't pay until I have that in writing."
B21: Script: Personal Loan
B22: Before you call | C22: Personal loans are harder to negotiate rate-wise, but you can often request a hardship plan, skip-a-payment option, or refinance at a lower rate. Have your loan number and balance ready.
B23: Opening line | C23: "Hi, I'm calling about my personal loan account [number]. I'm working to pay this down faster and I want to discuss options for reducing my rate or payments."
B24: The ask — refinance | C24: "Do you offer refinancing for existing customers? I'd like to explore whether I can get a lower rate given my payment history."
B25: The ask — hardship | C25: "I'm going through a temporary financial hardship. Is there a hardship program or temporary rate reduction available while I get back on track?"
B26: If they say no | C26: "Can you review my account and tell me what would qualify me for a better rate? I'd like to work toward that."
B27: Close | C27: "Thank you. Can you note this call on my account and send me any options in writing?"

Sheet Fear Reset
B2: Fear Reset — Your Personalized Mindset Fix
B3: =IF(Setup!D9="","Fill in Input 5 on Setup tab","Your fear: "&Setup!D9) -> Your fear: I'll never pay it all off
B5: If your fear is: "I'll never pay it all off"
B6: → | C6: The math proof | D6: Open the Snowball Schedule tab. Find the cumulative months column for your last debt. That number is your finish line. Most people are shocked it's under 3 years.
B7: → | C7: Reframe | D7: You're not paying off debt 'someday.' You have a date. The system just calculated it. Every payment moves that date closer.
B8: → | C8: Your finish-line formula | D8: Total debt ÷ total monthly attack = months to debt-free. Write that date on a sticky note. That date is real.
B9: → | C9: Action this week | D9: Calculate your finish-line date from the Snowball Schedule. Write it down. Set a calendar reminder for that month with the note: 'Debt-free date.'
B10: → | C10: When the fear returns | D10: Reopen the Snowball Schedule. Look at your cumulative months column. Numbers don't lie. Feelings do.
B12: If your fear is: "I'll mess up and miss a payment"
B13: → | C13: Auto-pay checklist | D13: Step 1: Log into each creditor's website. Step 2: Enable autopay for at least the minimum payment. Step 3: Set a calendar reminder 3 days before each due date as a backup.
B14: → | C14: The buffer rule | D14: Keep $200–$300 in checking beyond your normal spending. This is your 'forgot to transfer' buffer. It covers one missed autopay without late fees.
B15: → | C15: What happens if you miss one | D15: A single missed payment triggers a late fee ($25–$40) and a potential rate hike — not a catastrophe. Call the creditor the same day and ask for a one-time fee waiver. They usually say yes.
B16: → | C16: Action this week | D16: Set up autopay for your quick-win debt today. It takes 5 minutes. Use the minimum payment amount — you'll manually add the extra on top.
B17: → | C17: Build the habit | D17: Every payday: open your bank app, verify the autopay transferred, make your extra payment manually. Two minutes. Every payday.
B19: If your fear is: "I don't know if I'm doing this right"
B20: → | C20: Snowball validation — 3 checks | D20: Check 1: Are you paying minimums on all debts except #1? Check 2: Is 100% of your extra payment going to debt #1? Check 3: Are you not adding new debt? If yes to all 3 — you are doing it right.
B21: → | C21: Why snowball works | D21: Smallest balance first gives you the fastest psychological win. Research shows momentum from quick wins leads to higher total payoff rates than mathematically optimal (avalanche) methods.
B22: → | C22: The only mistake | D22: The only way to do this wrong is to stop. Slow payments, inconsistent amounts, missed weeks — all fine. Stopping = the only wrong answer.
B23: → | C23: What to ignore | D23: Ignore anyone who says avalanche (highest rate first) is better. It's marginally better mathematically. Snowball is better behaviorally. You bought this kit — stick to it.
B24: → | C24: Your progress check | D24: Open the 30-Day Kill Plan tab. If you made at least one extra payment this month beyond the minimum — you are ahead of 80% of people with debt. Keep going.
