Workbook

Sheet 📊 Dashboard
A1: 💼 Cash in Blue LLC — Personal Finance Dashboard
A2: Owner: Thomas Perdana | Updated: March 2026
B4: Net Worth | C4: Monthly Revenue | D4: Monthly Expenses | E4: Savings Rate | F4: Total Debt | G4: Cash on Hand
B5: ='📈 Net Worth'!C5 -> Cash | C5: ='💼 Business Revenue'!C3 -> 30000 | D5: ='💳 Expenses'!C3 -> 3421 | E5: =IF('💼 Business Revenue'!C3=0,0,('💼 Business Revenue'!C3-'💳 Expenses'!C3)/'💼 Business Revenue'!C3) -> 0.88596667 | F5: ='🏦 Debt Tracker'!C3 -> 60200 | G5: =B5 -> Cash
A8: 📊 Revenue by Stream (This Month)
A9: Revenue Stream | B9: Target ($) | C9: Actual ($) | D9: % of Target
A10: GEO/SEO Clients | B10: 3000 | C10: ='💼 Business Revenue'!C9 -> 12600 | D10: =IF(B10=0,0,C10/B10) -> 4.2
A11: Life Insurance Commissions | B11: 2000 | C11: ='💼 Business Revenue'!C10 -> 5400 | D11: =IF(B11=0,0,C11/B11) -> 2.7
A12: Loan Referrals | B12: 1500 | C12: ='💼 Business Revenue'!C11 -> 3600 | D12: =IF(B12=0,0,C12/B12) -> 2.4
A13: AI Partnerships | B13: 2500 | C13: ='💼 Business Revenue'!C12 -> 7500 | D13: =IF(B13=0,0,C13/B13) -> 3
A14: Other | B14: 500 | C14: ='💼 Business Revenue'!C13 -> 900 | D14: =IF(B14=0,0,C14/B14) -> 1.8
A15: TOTAL | B15: =SUM(B10:B14) -> 9500 | C15: =SUM(C10:C14) -> 30000 | D15: =IF(B15=0,0,C15/B15) -> 3.1578947
F17: 💰 Savings Goals
A18: Goal | B18: Progress | C18: Target
F19: Emergency Fund | G19: ='💰 Savings Goals'!C9 -> 28200 | H19: ='💰 Savings Goals'!B9 -> 145000
F20: First $100K | G20: ='💰 Savings Goals'!C10 -> 0 | H20: ='💰 Savings Goals'!B10 -> 0
F21: Investment Fund | G21: ='💰 Savings Goals'!C11 -> 0 | H21: ='💰 Savings Goals'!B11 -> 0

Sheet 💼 Business Revenue
A1: 💼 Business Revenue — Cash in Blue LLC
A2: Monthly Summary
A3: Total Revenue ($): | C3: =SUM(C9:C13) -> 30000
A4: Total Expenses ($): | C4: ='💳 Expenses'!C3 -> 3421
A5: Net Profit ($): | C5: =C3-C4 -> 26579
A7: Income Streams
A8: Revenue Stream | B8: This Month ($) | C8: YTD ($) | D8: Target (Mo) | E8: vs Target | F8: Notes
A9: GEO/SEO Clients | B9: 4200 | C9: 12600 | D9: 4000 | E9: =IF(D9=0,0,B9/D9-1) -> 0.05
A10: Life Insurance Commissions | B10: 1800 | C10: 5400 | D10: 2000 | E10: =IF(D10=0,0,B10/D10-1) -> -0.1
A11: Loan Referrals | B11: 1200 | C11: 3600 | D11: 1500 | E11: =IF(D11=0,0,B11/D11-1) -> -0.2
A12: AI Partnerships | B12: 2500 | C12: 7500 | D12: 2500 | E12: =IF(D12=0,0,B12/D12-1) -> 0
A13: Other / Misc | B13: 300 | C13: 900 | D13: 500 | E13: =IF(D13=0,0,B13/D13-1) -> -0.4
A14: TOTAL | B14: =SUM(B9:B13) -> 10000 | C14: =SUM(C9:C13) -> 30000 | D14: =SUM(D9:D13) -> 10500 | E14: =IF(D14=0,0,B14/D14-1) -> -0.047619048
A17: Monthly Revenue Log
A18: Month | B18: GEO/SEO | C18: Insurance | D18: Loans | E18: AI Partners | F18: Other | G18: Total
A19: Jan | B19: 0 | C19: 0 | D19: 0 | E19: 0 | F19: 0 | G19: =SUM(B19:F19) -> 0
A20: Feb | B20: 0 | C20: 0 | D20: 0 | E20: 0 | F20: 0 | G20: =SUM(B20:F20) -> 0
A21: Mar | B21: 0 | C21: 0 | D21: 0 | E21: 0 | F21: 0 | G21: =SUM(B21:F21) -> 0
A22: Apr | B22: 0 | C22: 0 | D22: 0 | E22: 0 | F22: 0 | G22: =SUM(B22:F22) -> 0
A23: May | B23: 0 | C23: 0 | D23: 0 | E23: 0 | F23: 0 | G23: =SUM(B23:F23) -> 0
A24: Jun | B24: 0 | C24: 0 | D24: 0 | E24: 0 | F24: 0 | G24: =SUM(B24:F24) -> 0
A25: Jul | B25: 0 | C25: 0 | D25: 0 | E25: 0 | F25: 0 | G25: =SUM(B25:F25) -> 0
A26: Aug | B26: 0 | C26: 0 | D26: 0 | E26: 0 | F26: 0 | G26: =SUM(B26:F26) -> 0
A27: Sep | B27: 0 | C27: 0 | D27: 0 | E27: 0 | F27: 0 | G27: =SUM(B27:F27) -> 0
A28: Oct | B28: 0 | C28: 0 | D28: 0 | E28: 0 | F28: 0 | G28: =SUM(B28:F28) -> 0
A29: Nov | B29: 0 | C29: 0 | D29: 0 | E29: 0 | F29: 0 | G29: =SUM(B29:F29) -> 0
A30: Dec | B30: 0 | C30: 0 | D30: 0 | E30: 0 | F30: 0 | G30: =SUM(B30:F30) -> 0

Sheet 💳 Expenses
A1: 💳 Expense Tracker — Personal & Business
A3: Total Expenses ($): | C3: =SUM(E9:E40) -> 3421
A4: LLC Deductible Total: | C4: =SUMIF(F9:F40,"Yes",E9:E40) -> 891
A7: Expense Log
A8: Date | B8: Category | C8: Description | D8: Type | E8: Amount ($) | F8: LLC Deductible? | G8: Notes
A9: 2026-03-01 | B9: Housing | C9: Rent | D9: Personal | E9: 1800 | F9: No
A10: 2026-03-01 | B10: Utilities | C10: Electric / Internet | D10: Personal | E10: 180 | F10: No
A11: 2026-03-05 | B11: Food | C11: Groceries | D11: Personal | E11: 350 | F11: No
A12: 2026-03-10 | B12: Transport | C12: Car insurance | D12: Personal | E12: 120 | F12: No
A13: 2026-03-12 | B13: Health | C13: Gym membership | D13: Personal | E13: 50 | F13: No
A14: 2026-03-15 | B14: Subscriptions | C14: Netflix / Spotify | D14: Personal | E14: 30 | F14: No
A15: 2026-03-15 | B15: Marketing | C15: Google Ads — GEO | D15: Business | E15: 400 | F15: Yes | G15: Advertising
A16: 2026-03-16 | B16: Software | C16: CRM subscription | D16: Business | E16: 99 | F16: Yes | G16: Tools
A17: 2026-03-18 | B17: Education | C17: Online course | D17: Business | E17: 197 | F17: Yes | G17: Professional dev
A18: 2026-03-20 | B18: Phone | C18: Business phone plan | D18: Business | E18: 65 | F18: Yes
A19: 2026-03-22 | B19: Meals | C19: Client lunch | D19: Business | E19: 85 | F19: Yes | G19: 50% deductible
A20: 2026-03-25 | B20: Office | C20: Supplies | D20: Business | E20: 45 | F20: Yes

Sheet 📅 Budget
A1: 📅 Monthly Budget — Actual vs. Target
A3: Category | B3: Budget ($) | C3: Actual ($) | D3: Variance ($) | E3: Variance % | F3: Status | G3: Notes
A4: Housing | B4: 1800 | C4: ='💳 Expenses'!E9 -> 1800 | D4: =B4-C4 -> 0 | E4: =IF(B4=0,0,(B4-C4)/B4) -> 0 | F4: =IF(D4>=0,"✅ Under","⚠️ Over") -> ✅ Under
A5: Utilities | B5: 200 | C5: ='💳 Expenses'!E10 -> 180 | D5: =B5-C5 -> 20 | E5: =IF(B5=0,0,(B5-C5)/B5) -> 0.1 | F5: =IF(D5>=0,"✅ Under","⚠️ Over") -> ✅ Under
A6: Food / Groceries | B6: 400 | C6: ='💳 Expenses'!E11 -> 350 | D6: =B6-C6 -> 50 | E6: =IF(B6=0,0,(B6-C6)/B6) -> 0.125 | F6: =IF(D6>=0,"✅ Under","⚠️ Over") -> ✅ Under
A7: Transport | B7: 150 | C7: ='💳 Expenses'!E12 -> 120 | D7: =B7-C7 -> 30 | E7: =IF(B7=0,0,(B7-C7)/B7) -> 0.2 | F7: =IF(D7>=0,"✅ Under","⚠️ Over") -> ✅ Under
A8: Health | B8: 100 | C8: ='💳 Expenses'!E13 -> 50 | D8: =B8-C8 -> 50 | E8: =IF(B8=0,0,(B8-C8)/B8) -> 0.5 | F8: =IF(D8>=0,"✅ Under","⚠️ Over") -> ✅ Under
A9: Subscriptions | B9: 50 | C9: ='💳 Expenses'!E14 -> 30 | D9: =B9-C9 -> 20 | E9: =IF(B9=0,0,(B9-C9)/B9) -> 0.4 | F9: =IF(D9>=0,"✅ Under","⚠️ Over") -> ✅ Under
A10: Marketing (Biz) | B10: 500 | C10: ='💳 Expenses'!E15 -> 400 | D10: =B10-C10 -> 100 | E10: =IF(B10=0,0,(B10-C10)/B10) -> 0.2 | F10: =IF(D10>=0,"✅ Under","⚠️ Over") -> ✅ Under
A11: Software (Biz) | B11: 150 | C11: ='💳 Expenses'!E16 -> 99 | D11: =B11-C11 -> 51 | E11: =IF(B11=0,0,(B11-C11)/B11) -> 0.34 | F11: =IF(D11>=0,"✅ Under","⚠️ Over") -> ✅ Under
A12: Education | B12: 200 | C12: ='💳 Expenses'!E17 -> 197 | D12: =B12-C12 -> 3 | E12: =IF(B12=0,0,(B12-C12)/B12) -> 0.015 | F12: =IF(D12>=0,"✅ Under","⚠️ Over") -> ✅ Under
A13: Phone | B13: 80 | C13: ='💳 Expenses'!E18 -> 65 | D13: =B13-C13 -> 15 | E13: =IF(B13=0,0,(B13-C13)/B13) -> 0.1875 | F13: =IF(D13>=0,"✅ Under","⚠️ Over") -> ✅ Under
A14: Meals / Ent. | B14: 150 | C14: ='💳 Expenses'!E19 -> 85 | D14: =B14-C14 -> 65 | E14: =IF(B14=0,0,(B14-C14)/B14) -> 0.43333333 | F14: =IF(D14>=0,"✅ Under","⚠️ Over") -> ✅ Under
A15: Office Supplies | B15: 60 | C15: ='💳 Expenses'!E20 -> 45 | D15: =B15-C15 -> 15 | E15: =IF(B15=0,0,(B15-C15)/B15) -> 0.25 | F15: =IF(D15>=0,"✅ Under","⚠️ Over") -> ✅ Under
A16: Miscellaneous | B16: 200 | C16: 0 | D16: =B16-C16 -> 200 | E16: =IF(B16=0,0,(B16-C16)/B16) -> 1 | F16: =IF(D16>=0,"✅ Under","⚠️ Over") -> ✅ Under
A17: TOTAL | B17: =SUM(B4:B16) -> 4040 | C17: =SUM(C4:C16) -> 3421 | D17: =B17-C17 -> 619 | E17: =IF(B17=0,0,(B17-C17)/B17) -> 0.15321782

Sheet 💰 Savings Goals
A1: 💰 Savings Goals — Progress Tracker
A3: Goal Name | B3: Target ($) | C3: Saved ($) | D3: Remaining ($) | E3: % Complete | F3: Monthly Add | G3: ETA (months)
A4: Emergency Fund (3 mo.) | B4: 9000 | C4: 3200 | D4: =B4-C4 -> 5800 | E4: =IF(B4=0,0,C4/B4) -> 0.35555556 | F4: 500 | G4: =IF(F4=0,"N/A",CEILING(D4/F4,1)) -> 12
A5: First $100K Milestone | B5: 100000 | C5: 18500 | D5: =B5-C5 -> 81500 | E5: =IF(B5=0,0,C5/B5) -> 0.185 | F5: 1000 | G5: =IF(F5=0,"N/A",CEILING(D5/F5,1)) -> 82
A6: Investment / Brokerage | B6: 25000 | C6: 4200 | D6: =B6-C6 -> 20800 | E6: =IF(B6=0,0,C6/B6) -> 0.168 | F6: 750 | G6: =IF(F6=0,"N/A",CEILING(D6/F6,1)) -> 28
A7: Vehicle Down Payment | B7: 8000 | C7: 1500 | D7: =B7-C7 -> 6500 | E7: =IF(B7=0,0,C7/B7) -> 0.1875 | F7: 400 | G7: =IF(F7=0,"N/A",CEILING(D7/F7,1)) -> 17
A8: Vacation / Travel Fund | B8: 3000 | C8: 800 | D8: =B8-C8 -> 2200 | E8: =IF(B8=0,0,C8/B8) -> 0.26666667 | F8: 200 | G8: =IF(F8=0,"N/A",CEILING(D8/F8,1)) -> 11
A9: TOTAL | B9: =SUM(B4:B8) -> 145000 | C9: =SUM(C4:C8) -> 28200 | D9: =SUM(D4:D8) -> 116800 | E9: =IF(B9=0,0,C9/B9) -> 0.19448276 | F9: =SUM(F4:F8) -> 2850

Sheet 🏦 Debt Tracker
A1: 🏦 Debt Tracker — Payoff Planner
A3: Total Debt ($): | C3: =SUM(C8:C15) -> 60200
A4: Total Monthly Payments: | C4: =SUM(E8:E15) -> 1300
A7: Creditor | B7: Type | C7: Balance ($) | D7: APR (%) | E7: Min Payment ($) | F7: Extra ($) | G7: Total Payment | H7: Payoff Date
A8: Chase Sapphire | B8: Credit Card | C8: 4200 | D8: 0.2499 | E8: 105 | F8: 200 | G8: =E8+F8 -> 305 | H8: =IF(OR(G8=0,D8=0),"N/A",TEXT(TODAY()+CEILING(C8/G8,1)*30,"mmm-yyyy")) -> May-2027
A9: Capital One | B9: Credit Card | C9: 1800 | D9: 0.1999 | E9: 45 | F9: 100 | G9: =E9+F9 -> 145 | H9: =IF(OR(G9=0,D9=0),"N/A",TEXT(TODAY()+CEILING(C9/G9,1)*30,"mmm-yyyy")) -> Apr-2027
A10: Student Loan | B10: Federal Loan | C10: 8500 | D10: 0.0505 | E10: 95 | F10: 50 | G10: =E10+F10 -> 145 | H10: =IF(OR(G10=0,D10=0),"N/A",TEXT(TODAY()+CEILING(C10/G10,1)*30,"mmm-yyyy")) -> Feb-2031
A11: Car Note | B11: Auto Loan | C11: 12400 | D11: 0.0675 | E11: 285 | F11: 0 | G11: =E11+F11 -> 285 | H11: =IF(OR(G11=0,D11=0),"N/A",TEXT(TODAY()+CEILING(C11/G11,1)*30,"mmm-yyyy")) -> Nov-2029
A12: Personal Loan | B12: Installment | C12: 3200 | D12: 0.125 | E12: 120 | F12: 80 | G12: =E12+F12 -> 200 | H12: =IF(OR(G12=0,D12=0),"N/A",TEXT(TODAY()+CEILING(C12/G12,1)*30,"mmm-yyyy")) -> Jul-2027
A13: TOTAL | C13: =SUM(C8:C12) -> 30100 | E13: =SUM(E8:E12) -> 650 | F13: =SUM(F8:F12) -> 430 | G13: =SUM(G8:G12) -> 1080

Sheet 📈 Net Worth
A1: 📈 Net Worth Tracker — Assets vs. Liabilities
A3: ASSETS
A4: Asset | B4: Value ($) | C4: Category | D4: Notes
A5: Checking Account | B5: 5200 | C5: Cash
A6: Savings Account | B6: 3800 | C6: Cash
A7: Business Checking | B7: 7400 | C7: Cash
A8: Brokerage / Investments | B8: 4200 | C8: Investments
A9: 401k / Retirement | B9: 9500 | C9: Retirement
A10: Vehicle (est. value) | B10: 14000 | C10: Property
A11: Other Assets | B11: 0 | C11: Other
A12: TOTAL ASSETS | B12: =SUM(B5:B11) -> 44100
A14: LIABILITIES
A15: Liability | B15: Balance ($) | C15: Type | D15: Notes
A16: Credit Card (Chase) | B16: 4200 | C16: Credit Card
A17: Credit Card (CapOne) | B17: 1800 | C17: Credit Card
A18: Student Loan | B18: 8500 | C18: Student Loan
A19: Car Note | B19: 12400 | C19: Auto Loan
A20: Personal Loan | B20: 3200 | C20: Installment
A21: TOTAL LIABILITIES | B21: =SUM(B16:B20) -> 30100
A24: NET WORTH | C24: =B12-B21 -> 14000
A27: Monthly Snapshot Log
A28: Month | B28: Total Assets ($) | C28: Total Liabilities ($) | D28: Net Worth ($) | E28: Change ($)
A29: Jan 2026 | B29: 43100 | C29: 30100 | D29: =B29-C29 -> 13000 | E29: -
A30: Feb 2026 | B30: 44200 | C30: 29500 | D30: =B30-C30 -> 14700 | E30: =D30-D29 -> 1700
A31: Mar 2026 | B31: 44100 | C31: 30100 | D31: =B31-C31 -> 14000 | E31: =D31-D30 -> -700

Sheet 🧾 Tax Estimate
A1: 🧾 Tax Estimate — Self-Employment & Quarterly Payments
A3: Assumptions (Blue = Edit Me)
A4: Annual Gross Revenue ($) | B4: 120000
A5: LLC Deductible Expenses ($) | B5: 12000
A6: Other Deductions (Standard / QBI) ($) | B6: 14600
A7: SE Tax Rate | B7: 0.153
A8: Federal Income Tax Rate (est.) | B8: 0.22
A9: State Income Tax Rate | B9: 0
A12: Calculated Tax Figures
A13: Net Self-Employment Income | B13: =B4-B5 -> 108000
A14: SE Tax (×15.3%) | B14: =(B13*0.9235)*B7 -> 15259.914
A15: SE Tax Deduction (½ SE tax) | B15: =B14/2 -> 7629.957
A16: QBI Deduction (20% of net) | B16: =B13*0.2 -> 21600
A17: Adjusted Gross Income | B17: =B13-B15-B6 -> 85770.043
A18: Estimated Federal Income Tax | B18: =B17*B8 -> 18869.409
A19: State Income Tax | B19: =B17*B9 -> 0
A20: TOTAL TAX DUE (Annual) | B20: =B14+B18+B19 -> 34129.323
A21: Effective Rate | B21: =IF(B4=0,0,B20/B4) -> 0.28441103
A25: Quarterly Estimated Payments
A26: Quarter | B26: Due Date | C26: Payment ($) | D26: Paid ($) | E26: Status
A27: Q1 2026 | B27: Apr 15, 2026 | C27: =B20/4 -> 8532.3309 | D27: 0 | E27: =IF(D27>=C27,"✅ Paid","⚠️ Due") -> ⚠️ Due
A28: Q2 2026 | B28: Jun 16, 2026 | C28: =B20/4 -> 8532.3309 | D28: 0 | E28: =IF(D28>=C28,"✅ Paid","⚠️ Due") -> ⚠️ Due
A29: Q3 2026 | B29: Sep 15, 2026 | C29: =B20/4 -> 8532.3309 | D29: 0 | E29: =IF(D29>=C29,"✅ Paid","⚠️ Due") -> ⚠️ Due
A30: Q4 2026 | B30: Jan 15, 2027 | C30: =B20/4 -> 8532.3309 | D30: 0 | E30: =IF(D30>=C30,"✅ Paid","⚠️ Due") -> ⚠️ Due
