Workbook

Sheet DASHBOARD
B2: PERSONAL FINANCE DASHBOARD
B3: =TEXT(TODAY(),"MMMM YYYY") -> March 2026
B5: NET WORTH | C5: MONTHLY CASH FLOW | D5: SAVINGS RATE | E5: BUDGET HEALTH
B6: ='NET WORTH'!B27 -> 234000 | C6: =BUDGET!B34 -> 3122 | D6: =BUDGET!B35 -> 0.53827586 | E6: =BUDGET!B36 -> 0.37793264
B7: ▲ Live — updates automatically | C7: ▲ Live — updates automatically | D7: ▲ Live — updates automatically | E7: ▲ Live — updates automatically
B9: BUDGET STATUS — THIS MONTH
B10: Category | C10: Actual This Month | D10: Remaining Budget
B11: Housing | C11: =SUMPRODUCT((Transactions[Type]="Expense")*(Transactions[Category]="Housing")*(Transactions[Month]=TEXT(TODAY(),"YYYY-MM"))*Transactions[Amount]) -> 2000 | D11: =2200-C11 -> 200
B12: Groceries | C12: =SUMPRODUCT((Transactions[Type]="Expense")*(Transactions[Category]="Groceries")*(Transactions[Month]=TEXT(TODAY(),"YYYY-MM"))*Transactions[Amount]) -> 185 | D12: =500-C12 -> 315
B13: Dining Out | C13: =SUMPRODUCT((Transactions[Type]="Expense")*(Transactions[Category]="Dining Out")*(Transactions[Month]=TEXT(TODAY(),"YYYY-MM"))*Transactions[Amount]) -> 85 | D13: =200-C13 -> 115
B14: Transportation | C14: =SUMPRODUCT((Transactions[Type]="Expense")*(Transactions[Category]="Transportation")*(Transactions[Month]=TEXT(TODAY(),"YYYY-MM"))*Transactions[Amount]) -> 0 | D14: =100-C14 -> 100
B15: Utilities | C15: =SUMPRODUCT((Transactions[Type]="Expense")*(Transactions[Category]="Utilities")*(Transactions[Month]=TEXT(TODAY(),"YYYY-MM"))*Transactions[Amount]) -> 120 | D15: =150-C15 -> 30
B16: Subscriptions | C16: =SUMPRODUCT((Transactions[Type]="Expense")*(Transactions[Category]="Subscriptions")*(Transactions[Month]=TEXT(TODAY(),"YYYY-MM"))*Transactions[Amount]) -> 18 | D16: =50-C16 -> 32
B19: CASH FLOW PROJECTION — NEXT 90 DAYS
B20: Current Balance | C20: ='CASH FLOW'!B3 -> 5000
B21: 30-Day Projected | C21: ='CASH FLOW'!E48 -> 7902
B22: 60-Day Projected | C22: ='CASH FLOW'!E78 -> 10804
B23: 90-Day Projected | C23: ='CASH FLOW'!E108 -> 13706
B26: MORTGAGE SNAPSHOT
B27: Monthly Payment | C27: =MORTGAGE!B13 -> 2075.5139
B28: Total Interest (life of loan) | C28: =MORTGAGE!E392 -> 427185.01
B29: Home Equity | C29: ='NET WORTH'!B28 -> 80000
B30: Remaining Balance | C30: ='NET WORTH'!B16 -> 320000
B33: Blue = input cells you change | Black = formulas | Green = cross-sheet links | Update transactions monthly in the TRANSACTIONS tab

Sheet TRANSACTIONS
A1: Date | B1: Description | C1: Category | D1: Amount | E1: Type | F1: Account | G1: Month
A2: 46082 | B2: Employer Paycheck | C2: Salary | D2: 5000 | E2: Income | F2: Chase Checking | G2: =TEXT(A2,"YYYY-MM") -> 2026-03
A3: 46083 | B3: Rent Payment | C3: Housing | D3: 2000 | E3: Expense | F3: Chase Checking | G3: =TEXT(A3,"YYYY-MM") -> 2026-03
A4: 46086 | B4: Whole Foods | C4: Groceries | D4: 185 | E4: Expense | F4: Amex | G4: =TEXT(A4,"YYYY-MM") -> 2026-03
A5: 46089 | B5: Netflix | C5: Subscriptions | D5: 18 | E5: Expense | F5: Amex | G5: =TEXT(A5,"YYYY-MM") -> 2026-03
A6: 46091 | B6: Electric Bill | C6: Utilities | D6: 120 | E6: Expense | F6: Chase Checking | G6: =TEXT(A6,"YYYY-MM") -> 2026-03
A7: 46093 | B7: Shell Gas Station | C7: Gas | D7: 55 | E7: Expense | F7: Amex | G7: =TEXT(A7,"YYYY-MM") -> 2026-03
A8: 46096 | B8: Restaurant Dinner | C8: Dining Out | D8: 85 | E8: Expense | F8: Amex | G8: =TEXT(A8,"YYYY-MM") -> 2026-03
A9: 46099 | B9: Car Insurance | C9: Insurance | D9: 150 | E9: Expense | F9: Chase Checking | G9: =TEXT(A9,"YYYY-MM") -> 2026-03
A10: 46101 | B10: Amazon Purchase | C10: Other Expense | D10: 65 | E10: Expense | F10: Amex | G10: =TEXT(A10,"YYYY-MM") -> 2026-03
A11: 46103 | B11: Freelance Project | C11: Freelance Income | D11: 800 | E11: Income | F11: Chase Checking | G11: =TEXT(A11,"YYYY-MM") -> 2026-03

Sheet BUDGET
A1: BUDGET — Current Month
A2: INCOME
A3: Category | B3: Budgeted | C3: Actual (This Month) | D3: Variance | E3: % of Budget
A4: Salary | B4: 5000 | C4: =SUMPRODUCT((Transactions[Type]="Income")*(Transactions[Category]=A4)*(Transactions[Month]=TEXT(TODAY(),"YYYY-MM"))*Transactions[Amount]) -> 5000 | D4: =C4-B4 -> 0 | E4: =IFERROR(C4/B4,0) -> 1
A5: Freelance Income | B5: 800 | C5: =SUMPRODUCT((Transactions[Type]="Income")*(Transactions[Category]=A5)*(Transactions[Month]=TEXT(TODAY(),"YYYY-MM"))*Transactions[Amount]) -> 800 | D5: =C5-B5 -> 0 | E5: =IFERROR(C5/B5,0) -> 1
A6: Investment Income | B6: 0 | C6: =SUMPRODUCT((Transactions[Type]="Income")*(Transactions[Category]=A6)*(Transactions[Month]=TEXT(TODAY(),"YYYY-MM"))*Transactions[Amount]) -> 0 | D6: =C6-B6 -> 0 | E6: =IFERROR(C6/B6,0) -> 0
A7: Other Income | B7: 0 | C7: =SUMPRODUCT((Transactions[Type]="Income")*(Transactions[Category]=A7)*(Transactions[Month]=TEXT(TODAY(),"YYYY-MM"))*Transactions[Amount]) -> 0 | D7: =C7-B7 -> 0 | E7: =IFERROR(C7/B7,0) -> 0
A8: Total Income | B8: =SUM(B4:B7) -> 5800 | C8: =SUM(C4:C7) -> 5800 | D8: =SUM(D4:D7) -> 0 | E8: =IFERROR(C8/B8,0) -> 1
A10: EXPENSES
A11: Category | B11: Budgeted | C11: Actual (This Month) | D11: Remaining | E11: % Used
A12: Housing | B12: 2200 | C12: =SUMPRODUCT((Transactions[Type]="Expense")*(Transactions[Category]=A12)*(Transactions[Month]=TEXT(TODAY(),"YYYY-MM"))*Transactions[Amount]) -> 2000 | D12: =B12-C12 -> 200 | E12: =IFERROR(C12/B12,0) -> 0.90909091
A13: Utilities | B13: 150 | C13: =SUMPRODUCT((Transactions[Type]="Expense")*(Transactions[Category]=A13)*(Transactions[Month]=TEXT(TODAY(),"YYYY-MM"))*Transactions[Amount]) -> 120 | D13: =B13-C13 -> 30 | E13: =IFERROR(C13/B13,0) -> 0.8
A14: Groceries | B14: 500 | C14: =SUMPRODUCT((Transactions[Type]="Expense")*(Transactions[Category]=A14)*(Transactions[Month]=TEXT(TODAY(),"YYYY-MM"))*Transactions[Amount]) -> 185 | D14: =B14-C14 -> 315 | E14: =IFERROR(C14/B14,0) -> 0.37
A15: Dining Out | B15: 200 | C15: =SUMPRODUCT((Transactions[Type]="Expense")*(Transactions[Category]=A15)*(Transactions[Month]=TEXT(TODAY(),"YYYY-MM"))*Transactions[Amount]) -> 85 | D15: =B15-C15 -> 115 | E15: =IFERROR(C15/B15,0) -> 0.425
A16: Transportation | B16: 100 | C16: =SUMPRODUCT((Transactions[Type]="Expense")*(Transactions[Category]=A16)*(Transactions[Month]=TEXT(TODAY(),"YYYY-MM"))*Transactions[Amount]) -> 0 | D16: =B16-C16 -> 100 | E16: =IFERROR(C16/B16,0) -> 0
A17: Gas | B17: 80 | C17: =SUMPRODUCT((Transactions[Type]="Expense")*(Transactions[Category]=A17)*(Transactions[Month]=TEXT(TODAY(),"YYYY-MM"))*Transactions[Amount]) -> 55 | D17: =B17-C17 -> 25 | E17: =IFERROR(C17/B17,0) -> 0.6875
A18: Insurance | B18: 150 | C18: =SUMPRODUCT((Transactions[Type]="Expense")*(Transactions[Category]=A18)*(Transactions[Month]=TEXT(TODAY(),"YYYY-MM"))*Transactions[Amount]) -> 150 | D18: =B18-C18 -> 0 | E18: =IFERROR(C18/B18,0) -> 1
A19: Medical | B19: 50 | C19: =SUMPRODUCT((Transactions[Type]="Expense")*(Transactions[Category]=A19)*(Transactions[Month]=TEXT(TODAY(),"YYYY-MM"))*Transactions[Amount]) -> 0 | D19: =B19-C19 -> 50 | E19: =IFERROR(C19/B19,0) -> 0
A20: Entertainment | B20: 100 | C20: =SUMPRODUCT((Transactions[Type]="Expense")*(Transactions[Category]=A20)*(Transactions[Month]=TEXT(TODAY(),"YYYY-MM"))*Transactions[Amount]) -> 0 | D20: =B20-C20 -> 100 | E20: =IFERROR(C20/B20,0) -> 0
A21: Subscriptions | B21: 50 | C21: =SUMPRODUCT((Transactions[Type]="Expense")*(Transactions[Category]=A21)*(Transactions[Month]=TEXT(TODAY(),"YYYY-MM"))*Transactions[Amount]) -> 18 | D21: =B21-C21 -> 32 | E21: =IFERROR(C21/B21,0) -> 0.36
A22: Clothing | B22: 75 | C22: =SUMPRODUCT((Transactions[Type]="Expense")*(Transactions[Category]=A22)*(Transactions[Month]=TEXT(TODAY(),"YYYY-MM"))*Transactions[Amount]) -> 0 | D22: =B22-C22 -> 75 | E22: =IFERROR(C22/B22,0) -> 0
A23: Personal Care | B23: 50 | C23: =SUMPRODUCT((Transactions[Type]="Expense")*(Transactions[Category]=A23)*(Transactions[Month]=TEXT(TODAY(),"YYYY-MM"))*Transactions[Amount]) -> 0 | D23: =B23-C23 -> 50 | E23: =IFERROR(C23/B23,0) -> 0
... A26: Other Expense | B26: 100 | C26: =SUMPRODUCT((Transactions[Type]="Expense")*(Transactions[Category]=A26)*(Transactions[Month]=TEXT(TODAY(),"YYYY-MM"))*Transactions[Amount]) -> 65 | D26: =B26-C26 -> 35 | E26: =IFERROR(C26/B26,0) -> 0.65
A27: Total Expenses | B27: =SUM(B12:B26) -> 4305 | C27: =SUM(C12:C26) -> 2678 | D27: =SUM(D12:D26) -> 1627 | E27: =IFERROR(C27/B27,0) -> 0.62206736
A29: MONTHLY SUMMARY
A30: Total Income Budgeted | B30: =B8 -> 5800
A31: Total Income Actual | B31: =C8 -> 5800
A32: Total Expenses Budgeted | B32: =B27 -> 4305
A33: Total Expenses Actual | B33: =C27 -> 2678
A34: Net Cash Flow | B34: =C8-C27 -> 3122
A35: Savings Rate | B35: =IFERROR((C8-C27)/C8,0) -> 0.53827586
A36: Budget Health % | B36: =IFERROR(1-(C27/B27),0) -> 0.37793264

Sheet CASH FLOW
A1: CASH FLOW — 90-Day Projection
A3: Starting Balance (update monthly): | B3: 5000
A5: RECURRING TRANSACTIONS
A6: Description | B6: Amount | C6: Type | D6: Frequency | E6: Day of Month
A7: Salary | B7: 5000 | C7: Income | D7: Monthly | E7: 1
A8: Freelance Income | B8: 800 | C8: Income | D8: Monthly | E8: 15
A9: Rent | B9: 2000 | C9: Expense | D9: Monthly | E9: 1
A10: Car Insurance | B10: 150 | C10: Expense | D10: Monthly | E10: 15
A11: Netflix | B11: 18 | C11: Expense | D11: Monthly | E11: 22
A12: Utilities | B12: 150 | C12: Expense | D12: Monthly | E12: 10
A13: Groceries | B13: 500 | C13: Expense | D13: Monthly | E13: 5
A14: Gas | B14: 80 | C14: Expense | D14: Monthly | E14: 12
A17: 90-DAY PROJECTION
A18: Date | B18: Day | C18: Sched. Income | D18: Sched. Expense | E18: Projected Balance
A19: =TODAY() -> 46111 | B19: =TEXT(A19,"ddd") -> Mon | C19: =SUMPRODUCT((ScheduledTransactions[Type]="Income")*(DAY(A19)=ScheduledTransactions[Day of Month])*ScheduledTransactions[Amount]) -> 0 | D19: =SUMPRODUCT((ScheduledTransactions[Type]="Expense")*(DAY(A19)=ScheduledTransactions[Day of Month])*ScheduledTransactions[Amount]) -> 0 | E19: =B3+C19-D19 -> 5000
A20: =A19+1 -> 46112 | B20: =TEXT(A20,"ddd") -> Tue | C20: =SUMPRODUCT((ScheduledTransactions[Type]="Income")*(DAY(A20)=ScheduledTransactions[Day of Month])*ScheduledTransactions[Amount]) -> 0 | D20: =SUMPRODUCT((ScheduledTransactions[Type]="Expense")*(DAY(A20)=ScheduledTransactions[Day of Month])*ScheduledTransactions[Amount]) -> 0 | E20: =E19+C20-D20 -> 5000
A21: =A20+1 -> 46113 | B21: =TEXT(A21,"ddd") -> Wed | C21: =SUMPRODUCT((ScheduledTransactions[Type]="Income")*(DAY(A21)=ScheduledTransactions[Day of Month])*ScheduledTransactions[Amount]) -> 5000 | D21: =SUMPRODUCT((ScheduledTransactions[Type]="Expense")*(DAY(A21)=ScheduledTransactions[Day of Month])*ScheduledTransactions[Amount]) -> 2000 | E21: =E20+C21-D21 -> 8000
A22: =A21+1 -> 46114 | B22: =TEXT(A22,"ddd") -> Thu | C22: =SUMPRODUCT((ScheduledTransactions[Type]="Income")*(DAY(A22)=ScheduledTransactions[Day of Month])*ScheduledTransactions[Amount]) -> 0 | D22: =SUMPRODUCT((ScheduledTransactions[Type]="Expense")*(DAY(A22)=ScheduledTransactions[Day of Month])*ScheduledTransactions[Amount]) -> 0 | E22: =E21+C22-D22 -> 8000
A23: =A22+1 -> 46115 | B23: =TEXT(A23,"ddd") -> Fri | C23: =SUMPRODUCT((ScheduledTransactions[Type]="Income")*(DAY(A23)=ScheduledTransactions[Day of Month])*ScheduledTransactions[Amount]) -> 0 | D23: =SUMPRODUCT((ScheduledTransactions[Type]="Expense")*(DAY(A23)=ScheduledTransactions[Day of Month])*ScheduledTransactions[Amount]) -> 0 | E23: =E22+C23-D23 -> 8000
A24: =A23+1 -> 46116 | B24: =TEXT(A24,"ddd") -> Sat | C24: =SUMPRODUCT((ScheduledTransactions[Type]="Income")*(DAY(A24)=ScheduledTransactions[Day of Month])*ScheduledTransactions[Amount]) -> 0 | D24: =SUMPRODUCT((ScheduledTransactions[Type]="Expense")*(DAY(A24)=ScheduledTransactions[Day of Month])*ScheduledTransactions[Amount]) -> 0 | E24: =E23+C24-D24 -> 8000
A25: =A24+1 -> 46117 | B25: =TEXT(A25,"ddd") -> Sun | C25: =SUMPRODUCT((ScheduledTransactions[Type]="Income")*(DAY(A25)=ScheduledTransactions[Day of Month])*ScheduledTransactions[Amount]) -> 0 | D25: =SUMPRODUCT((ScheduledTransactions[Type]="Expense")*(DAY(A25)=ScheduledTransactions[Day of Month])*ScheduledTransactions[Amount]) -> 500 | E25: =E24+C25-D25 -> 7500
A26: =A25+1 -> 46118 | B26: =TEXT(A26,"ddd") -> Mon | C26: =SUMPRODUCT((ScheduledTransactions[Type]="Income")*(DAY(A26)=ScheduledTransactions[Day of Month])*ScheduledTransactions[Amount]) -> 0 | D26: =SUMPRODUCT((ScheduledTransactions[Type]="Expense")*(DAY(A26)=ScheduledTransactions[Day of Month])*ScheduledTransactions[Amount]) -> 0 | E26: =E25+C26-D26 -> 7500
A27: =A26+1 -> 46119 | B27: =TEXT(A27,"ddd") -> Tue | C27: =SUMPRODUCT((ScheduledTransactions[Type]="Income")*(DAY(A27)=ScheduledTransactions[Day of Month])*ScheduledTransactions[Amount]) -> 0 | D27: =SUMPRODUCT((ScheduledTransactions[Type]="Expense")*(DAY(A27)=ScheduledTransactions[Day of Month])*ScheduledTransactions[Amount]) -> 0 | E27: =E26+C27-D27 -> 7500
A28: =A27+1 -> 46120 | B28: =TEXT(A28,"ddd") -> Wed | C28: =SUMPRODUCT((ScheduledTransactions[Type]="Income")*(DAY(A28)=ScheduledTransactions[Day of Month])*ScheduledTransactions[Amount]) -> 0 | D28: =SUMPRODUCT((ScheduledTransactions[Type]="Expense")*(DAY(A28)=ScheduledTransactions[Day of Month])*ScheduledTransactions[Amount]) -> 0 | E28: =E27+C28-D28 -> 7500
A29: =A28+1 -> 46121 | B29: =TEXT(A29,"ddd") -> Thu | C29: =SUMPRODUCT((ScheduledTransactions[Type]="Income")*(DAY(A29)=ScheduledTransactions[Day of Month])*ScheduledTransactions[Amount]) -> 0 | D29: =SUMPRODUCT((ScheduledTransactions[Type]="Expense")*(DAY(A29)=ScheduledTransactions[Day of Month])*ScheduledTransactions[Amount]) -> 0 | E29: =E28+C29-D29 -> 7500
A30: =A29+1 -> 46122 | B30: =TEXT(A30,"ddd") -> Fri | C30: =SUMPRODUCT((ScheduledTransactions[Type]="Income")*(DAY(A30)=ScheduledTransactions[Day of Month])*ScheduledTransactions[Amount]) -> 0 | D30: =SUMPRODUCT((ScheduledTransactions[Type]="Expense")*(DAY(A30)=ScheduledTransactions[Day of Month])*ScheduledTransactions[Amount]) -> 150 | E30: =E29+C30-D30 -> 7350
A31: =A30+1 -> 46123 | B31: =TEXT(A31,"ddd") -> Sat | C31: =SUMPRODUCT((ScheduledTransactions[Type]="Income")*(DAY(A31)=ScheduledTransactions[Day of Month])*ScheduledTransactions[Amount]) -> 0 | D31: =SUMPRODUCT((ScheduledTransactions[Type]="Expense")*(DAY(A31)=ScheduledTransactions[Day of Month])*ScheduledTransactions[Amount]) -> 0 | E31: =E30+C31-D31 -> 7350
... A108: =A107+1 -> 46200 | B108: =TEXT(A108,"ddd") -> Sat | C108: =SUMPRODUCT((ScheduledTransactions[Type]="Income")*(DAY(A108)=ScheduledTransactions[Day of Month])*ScheduledTransactions[Amount]) -> 0 | D108: =SUMPRODUCT((ScheduledTransactions[Type]="Expense")*(DAY(A108)=ScheduledTransactions[Day of Month])*ScheduledTransactions[Amount]) -> 0 | E108: =E107+C108-D108 -> 13706

Sheet MORTGAGE
A1: MORTGAGE CALCULATOR & AMORTIZATION SCHEDULE
A3: LOAN INPUTS
A4: Home Price | B4: 400000
A5: Down Payment ($) | B5: 80000
A6: Down Payment (%) | B6: =B5/B4 -> 0.2
A7: Loan Amount | B7: =B4-B5 -> 320000
A8: Annual Interest Rate | B8: 0.0675
A9: Loan Term (Years) | B9: 30
A10: Monthly Interest Rate | B10: =B8/12 -> 0.005625
A11: Total Payments (months) | B11: =B9*12 -> 360
A12: Loan Start Date | B12: 46023
A13: Monthly Payment | B13: =PMT(B10,B11,-B7) -> 2075.5139
A15: EXTRA PAYMENT SCENARIO
A16: Extra Monthly Payment | B16: 0
A17: New Monthly Total | B17: =B13+B16 -> 2075.5139
A19: WHAT-IF COMPARISON
A20: Metric | B20: Standard Loan | C20: With Extra Payment
A21: Monthly Payment | B21: =B13 -> 2075.5139 | C21: =B17 -> 2075.5139
A22: Total Paid | B22: =B13*B11 -> 747185.01 | C22: =B17*CEILING(NPER(B10,-B17,-B7),1) -> -230382.04
A23: Total Interest | B23: =B13*B11-B7 -> 427185.01 | C23: =B17*CEILING(NPER(B10,-B17,-B7),1)-B7 -> -550382.04
A24: Payoff Date | B24: =EDATE(B12,B11) -> 56980 | C24: =EDATE(B12,CEILING(NPER(B10,-B17,-B7),1)) -> 42644
A25: Interest Saved | B25: — | C25: =C23-D23 -> -550382.04
A26: Months Saved | B26: — | C26: =B11-CEILING(NPER(B10,-B17,-B7),1) -> 471
A29: AMORTIZATION SCHEDULE (360 months)
A30: Payment # | B30: Payment Date | C30: Payment | D30: Principal | E30: Interest | F30: Balance
F31: =B7 -> 320000
A32: 1 | B32: =EDATE($B$12,A32) -> 46054 | C32: =$B$13 -> 2075.5139 | D32: =C32-E32 -> 275.51391 | E32: =F31*$B$10 -> 1800 | F32: =MAX(0,F31-D32) -> 319724.49
A33: 2 | B33: =EDATE($B$12,A33) -> 46082 | C33: =$B$13 -> 2075.5139 | D33: =C33-E33 -> 277.06367 | E33: =F32*$B$10 -> 1798.4502 | F33: =MAX(0,F32-D33) -> 319447.42
A34: 3 | B34: =EDATE($B$12,A34) -> 46113 | C34: =$B$13 -> 2075.5139 | D34: =C34-E34 -> 278.62216 | E34: =F33*$B$10 -> 1796.8918 | F34: =MAX(0,F33-D34) -> 319168.8
A35: 4 | B35: =EDATE($B$12,A35) -> 46143 | C35: =$B$13 -> 2075.5139 | D35: =C35-E35 -> 280.18941 | E35: =F34*$B$10 -> 1795.3245 | F35: =MAX(0,F34-D35) -> 318888.61
A36: 5 | B36: =EDATE($B$12,A36) -> 46174 | C36: =$B$13 -> 2075.5139 | D36: =C36-E36 -> 281.76547 | E36: =F35*$B$10 -> 1793.7484 | F36: =MAX(0,F35-D36) -> 318606.85
A37: 6 | B37: =EDATE($B$12,A37) -> 46204 | C37: =$B$13 -> 2075.5139 | D37: =C37-E37 -> 283.3504 | E37: =F36*$B$10 -> 1792.1635 | F37: =MAX(0,F36-D37) -> 318323.49
A38: 7 | B38: =EDATE($B$12,A38) -> 46235 | C38: =$B$13 -> 2075.5139 | D38: =C38-E38 -> 284.94425 | E38: =F37*$B$10 -> 1790.5697 | F38: =MAX(0,F37-D38) -> 318038.55
A39: 8 | B39: =EDATE($B$12,A39) -> 46266 | C39: =$B$13 -> 2075.5139 | D39: =C39-E39 -> 286.54706 | E39: =F38*$B$10 -> 1788.9668 | F39: =MAX(0,F38-D39) -> 317752
A40: 9 | B40: =EDATE($B$12,A40) -> 46296 | C40: =$B$13 -> 2075.5139 | D40: =C40-E40 -> 288.15889 | E40: =F39*$B$10 -> 1787.355 | F40: =MAX(0,F39-D40) -> 317463.84
A41: 10 | B41: =EDATE($B$12,A41) -> 46327 | C41: =$B$13 -> 2075.5139 | D41: =C41-E41 -> 289.77978 | E41: =F40*$B$10 -> 1785.7341 | F41: =MAX(0,F40-D41) -> 317174.06
A42: 11 | B42: =EDATE($B$12,A42) -> 46357 | C42: =$B$13 -> 2075.5139 | D42: =C42-E42 -> 291.40979 | E42: =F41*$B$10 -> 1784.1041 | F42: =MAX(0,F41-D42) -> 316882.66
A43: 12 | B43: =EDATE($B$12,A43) -> 46388 | C43: =$B$13 -> 2075.5139 | D43: =C43-E43 -> 293.04897 | E43: =F42*$B$10 -> 1782.4649 | F43: =MAX(0,F42-D43) -> 316589.61
... A391: 360 | B391: =EDATE($B$12,A391) -> 56980 | C391: =$B$13 -> 2075.5139 | D391: =C391-E391 -> 2063.9044 | E391: =F390*$B$10 -> 11.609463 | F391: =MAX(0,F390-D391) -> 1.8785613e-09
A392: TOTALS | C392: =SUM(C32:C391) -> 747185.01 | E392: =SUM(E32:E391) -> 427185.01

Sheet NET WORTH
A1: NET WORTH TRACKER
A3: ASSETS
A4: Asset | B4: Current Value | C4: Notes
A5: Checking Account | B5: 5000 | C5: Update monthly
A6: Savings Account | B6: 12000
A7: Investment Account | B7: 45000 | C7: Brokerage / taxable
A8: 401k / Retirement | B8: 85000
A9: Home Value | B9: 400000 | C9: Purchase price — update annually
A10: Vehicle(s) | B10: 22000
A11: Other Assets | B11: 0
A12: Total Assets | B12: =SUM(B5:B11) -> 569000
A14: LIABILITIES
A15: Liability | B15: Current Balance | C15: Notes
A16: Mortgage Balance | B16: 320000 | C16: Link to amortization or enter current balance
A17: Car Loan | B17: 15000
A18: Credit Card 1 | B18: 0
A19: Credit Card 2 | B19: 0
A20: Student Loans | B20: 0
A21: Other Debt | B21: 0
A22: Total Liabilities | B22: =SUM(B16:B21) -> 335000
A24: NET WORTH SUMMARY
A25: Total Assets | B25: =B12 -> 569000
A26: Total Liabilities | B26: =B22 -> 335000
A27: NET WORTH | B27: =B25-B26 -> 234000
A28: Home Equity | B28: =B9-B16 -> 80000
A29: Debt-to-Asset Ratio | B29: =IFERROR(B22/B12,0) -> 0.5887522
A32: MONTHLY SNAPSHOT — paste values here on 1st of each month
A33: Month | B33: Total Assets | C33: Total Liabilities | D33: Net Worth
A34: Jan 2026 | D34: =IF(B34<>"",B34-C34,"")
A35: Feb 2026 | D35: =IF(B35<>"",B35-C35,"")
A36: Mar 2026 | D36: =IF(B36<>"",B36-C36,"")
A37: Apr 2026 | D37: =IF(B37<>"",B37-C37,"")
A38: May 2026 | D38: =IF(B38<>"",B38-C38,"")
A39: Jun 2026 | D39: =IF(B39<>"",B39-C39,"")
A40: Jul 2026 | D40: =IF(B40<>"",B40-C40,"")
A41: Aug 2026 | D41: =IF(B41<>"",B41-C41,"")
A42: Sep 2026 | D42: =IF(B42<>"",B42-C42,"")
A43: Oct 2026 | D43: =IF(B43<>"",B43-C43,"")
A44: Nov 2026 | D44: =IF(B44<>"",B44-C44,"")
A45: Dec 2026 | D45: =IF(B45<>"",B45-C45,"")
